task4/bin2bcd.sv
// Design Name : bin2bcd
// File Name : bin2bcd.v
// Function : convert 8-bit binary number in to three BCD digits
// Author:  Peter Cheung
// Version: 2.0 (26 Aug 2022)00
//---------------------------------------------------
//ALGORITHM: (See explanation on course webpage)
//   Shift binary number x left by one bit at a time into temporary register 'result'
//   If bottom 4 bits of result  >= 5
//		add 3 (only once)
//   Continue shifting x into result until all bit in x have been processed


module bin2bcd (x, BCD);
	input[7:0] x;			// value ot be converted
	output reg[11:0] BCD;  // BCD digits
	
	 // Concatenation of input and output
   reg [19:0] result;  // no of bits = no_of_bit of x + 4* no of digits
   integer i;
   
   always_comb
   begin
      result[19:0] = 0;
      result[7:0] = x;

      for (i=0; i<8; i=i+1) begin
			// Check if unit digit >= 5
         if (result[11:8] >= 5)
            result[11:8] = result[11:8] + 4'd3;
				
         // Check if ten digita >= 5
         if (result[15:12] >= 5)
            result[15:12] = result[15:12] + 4'd3;

			// Shift everything left
         result = result << 1;
      end
      
      // Decode output from result
      BCD = result[19:8];
   end
	
endmodule

task4/counter.sv
module counter #(parameter WIDTH = 8)
(input logic clk, // Clock
 input logic rst, // Reset
 input logic en, // Counter enable
 output logic[WIDTH-1:0] count); // Counter output
    
    always_ff @(posedge clk)
        if (rst)
            count <= {WIDTH{1'b0}};
        else
            count <= count + {{WIDTH-1{1'b0}}, en};

endmodule

task4/top.sv
module top #(parameter WIDTH = 8)
(input wire clk, // Clock
 input wire rst, // Reset
 input wire en, // Enable
 output wire [11:0] bcd // Count output
);

    wire[WIDTH-1:0] count; // Interconnect wire

    counter myCounter(clk, rst, en, count);
    bin2bcd myDecoder(count, bcd);

endmodule

task4/top.vcd
$version Generated by VerilatedVcd $end
$date Tue Oct 25 21:29:10 2022 $end
$timescale 1ps $end

 $scope module TOP $end
  $var wire 12 & bcd [11:0] $end
  $var wire  1 # clk $end
  $var wire  1 % en $end
  $var wire  1 $ rst $end
  $scope module top $end
   $var wire 32 ) WIDTH [31:0] $end
   $var wire 12 & bcd [11:0] $end
   $var wire  1 # clk $end
   $var wire  8 ' count [7:0] $end
   $var wire  1 % en $end
   $var wire  1 $ rst $end
   $scope module myCounter $end
    $var wire 32 ) WIDTH [31:0] $end
    $var wire  1 # clk $end
    $var wire  8 ' count [7:0] $end
    $var wire  1 % en $end
    $var wire  1 $ rst $end
   $upscope $end
   $scope module myDecoder $end
    $var wire 12 & BCD [11:0] $end
    $var wire 32 * i [31:0] $end
    $var wire 20 ( result [19:0] $end
    $var wire  8 ' x [7:0] $end
   $upscope $end
  $upscope $end
 $upscope $end
$enddefinitions $end


#0
1#
0$
0%
b000000000000 &
b00000000 '
b00000000000000000000 (
b00000000000000000000000000001000 )
b00000000000000000000000000001000 *
#1
0#
#2
1#
1%
#3
0#
#4
1#
b000000000001 &
b00000001 '
b00000000000100000000 (
#5
0#
#6
1#
b000000000010 &
b00000010 '
b00000000001000000000 (
#7
0#
#8
1#
b000000000011 &
b00000011 '
b00000000001100000000 (
#9
0#
#10
1#
b000000000100 &
b00000100 '
b00000000010000000000 (
#11
0#
#12
1#
b000000000101 &
b00000101 '
b00000000010100000000 (
#13
0#
#14
1#
b000000000110 &
b00000110 '
b00000000011000000000 (
#15
0#
#16
1#
b000000000111 &
b00000111 '
b00000000011100000000 (
#17
0#
#18
1#
b000000001000 &
b00001000 '
b00000000100000000000 (
#19
0#
#20
1#
b000000001001 &
b00001001 '
b00000000100100000000 (
#21
0#
#22
1#
b000000010000 &
b00001010 '
b00000001000000000000 (
#23
0#
#24
1#
b000000010001 &
b00001011 '
b00000001000100000000 (
#25
0#
#26
1#
b000000010010 &
b00001100 '
b00000001001000000000 (
#27
0#
#28
1#
b000000010011 &
b00001101 '
b00000001001100000000 (
#29
0#
#30
1#
b000000010100 &
b00001110 '
b00000001010000000000 (
#31
0#
#32
1#
b000000010101 &
b00001111 '
b00000001010100000000 (
#33
0#
#34
1#
b000000010110 &
b00010000 '
b00000001011000000000 (
#35
0#
#36
1#
b000000010111 &
b00010001 '
b00000001011100000000 (
#37
0#
#38
1#
b000000011000 &
b00010010 '
b00000001100000000000 (
#39
0#
#40
1#
b000000011001 &
b00010011 '
b00000001100100000000 (
#41
0#
#42
1#
b000000100000 &
b00010100 '
b00000010000000000000 (
#43
0#
#44
1#
b000000100001 &
b00010101 '
b00000010000100000000 (
#45
0#
#46
1#
b000000100010 &
b00010110 '
b00000010001000000000 (
#47
0#
#48
1#
b000000100011 &
b00010111 '
b00000010001100000000 (
#49
0#
#50
1#
b000000100100 &
b00011000 '
b00000010010000000000 (
#51
0#
#52
1#
b000000100101 &
b00011001 '
b00000010010100000000 (
#53
0#
#54
1#
b000000100110 &
b00011010 '
b00000010011000000000 (
#55
0#
#56
1#
b000000100111 &
b00011011 '
b00000010011100000000 (
#57
0#
#58
1#
b000000101000 &
b00011100 '
b00000010100000000000 (
#59
0#
#60
1#
b000000101001 &
b00011101 '
b00000010100100000000 (
#61
0#
#62
1#
b000000110000 &
b00011110 '
b00000011000000000000 (
#63
0#
#64
1#
b000000110001 &
b00011111 '
b00000011000100000000 (
#65
0#
#66
1#
b000000110010 &
b00100000 '
b00000011001000000000 (
#67
0#
#68
1#
b000000110011 &
b00100001 '
b00000011001100000000 (
#69
0#
#70
1#
b000000110100 &
b00100010 '
b00000011010000000000 (
#71
0#
#72
1#
b000000110101 &
b00100011 '
b00000011010100000000 (
#73
0#
#74
1#
b000000110110 &
b00100100 '
b00000011011000000000 (
#75
0#
#76
1#
b000000110111 &
b00100101 '
b00000011011100000000 (
#77
0#
#78
1#
b000000111000 &
b00100110 '
b00000011100000000000 (
#79
0#
#80
1#
b000000111001 &
b00100111 '
b00000011100100000000 (
#81
0#
#82
1#
b000001000000 &
b00101000 '
b00000100000000000000 (
#83
0#
#84
1#
b000001000001 &
b00101001 '
b00000100000100000000 (
#85
0#
#86
1#
b000001000010 &
b00101010 '
b00000100001000000000 (
#87
0#
#88
1#
b000001000011 &
b00101011 '
b00000100001100000000 (
#89
0#
#90
1#
b000001000100 &
b00101100 '
b00000100010000000000 (
#91
0#
#92
1#
b000001000101 &
b00101101 '
b00000100010100000000 (
#93
0#
#94
1#
b000001000110 &
b00101110 '
b00000100011000000000 (
#95
0#
#96
1#
b000001000111 &
b00101111 '
b00000100011100000000 (
#97
0#
#98
1#
b000001001000 &
b00110000 '
b00000100100000000000 (
#99
0#
#100
1#
b000001001001 &
b00110001 '
b00000100100100000000 (
#101
0#
#102
1#
b000001010000 &
b00110010 '
b00000101000000000000 (
#103
0#
#104
1#
b000001010001 &
b00110011 '
b00000101000100000000 (
#105
0#
#106
1#
b000001010010 &
b00110100 '
b00000101001000000000 (
#107
0#
#108
1#
b000001010011 &
b00110101 '
b00000101001100000000 (
#109
0#
#110
1#
b000001010100 &
b00110110 '
b00000101010000000000 (
#111
0#
#112
1#
b000001010101 &
b00110111 '
b00000101010100000000 (
#113
0#
#114
1#
b000001010110 &
b00111000 '
b00000101011000000000 (
#115
0#
#116
1#
b000001010111 &
b00111001 '
b00000101011100000000 (
#117
0#
#118
1#
b000001011000 &
b00111010 '
b00000101100000000000 (
#119
0#
#120
1#
b000001011001 &
b00111011 '
b00000101100100000000 (
#121
0#
#122
1#
b000001100000 &
b00111100 '
b00000110000000000000 (
#123
0#
#124
1#
b000001100001 &
b00111101 '
b00000110000100000000 (
#125
0#
#126
1#
b000001100010 &
b00111110 '
b00000110001000000000 (
#127
0#
#128
1#
b000001100011 &
b00111111 '
b00000110001100000000 (
#129
0#
#130
1#
b000001100100 &
b01000000 '
b00000110010000000000 (
#131
0#
#132
1#
b000001100101 &
b01000001 '
b00000110010100000000 (
#133
0#
#134
1#
b000001100110 &
b01000010 '
b00000110011000000000 (
#135
0#
#136
1#
b000001100111 &
b01000011 '
b00000110011100000000 (
#137
0#
#138
1#
b000001101000 &
b01000100 '
b00000110100000000000 (
#139
0#
#140
1#
b000001101001 &
b01000101 '
b00000110100100000000 (
#141
0#
#142
1#
b000001110000 &
b01000110 '
b00000111000000000000 (
#143
0#
#144
1#
b000001110001 &
b01000111 '
b00000111000100000000 (
#145
0#
#146
1#
b000001110010 &
b01001000 '
b00000111001000000000 (
#147
0#
#148
1#
b000001110011 &
b01001001 '
b00000111001100000000 (
#149
0#
#150
1#
b000001110100 &
b01001010 '
b00000111010000000000 (
#151
0#
#152
1#
b000001110101 &
b01001011 '
b00000111010100000000 (
#153
0#
#154
1#
b000001110110 &
b01001100 '
b00000111011000000000 (
#155
0#
#156
1#
b000001110111 &
b01001101 '
b00000111011100000000 (
#157
0#
#158
1#
b000001111000 &
b01001110 '
b00000111100000000000 (
#159
0#
#160
1#
b000001111001 &
b01001111 '
b00000111100100000000 (
#161
0#
#162
1#
b000010000000 &
b01010000 '
b00001000000000000000 (
#163
0#
#164
1#
b000010000001 &
b01010001 '
b00001000000100000000 (
#165
0#
#166
1#
b000010000010 &
b01010010 '
b00001000001000000000 (
#167
0#
#168
1#
b000010000011 &
b01010011 '
b00001000001100000000 (
#169
0#
#170
1#
b000010000100 &
b01010100 '
b00001000010000000000 (
#171
0#
#172
1#
b000010000101 &
b01010101 '
b00001000010100000000 (
#173
0#
#174
1#
b000010000110 &
b01010110 '
b00001000011000000000 (
#175
0#
#176
1#
b000010000111 &
b01010111 '
b00001000011100000000 (
#177
0#
#178
1#
b000010001000 &
b01011000 '
b00001000100000000000 (
#179
0#
#180
1#
b000010001001 &
b01011001 '
b00001000100100000000 (
#181
0#
#182
1#
b000010010000 &
b01011010 '
b00001001000000000000 (
#183
0#
#184
1#
b000010010001 &
b01011011 '
b00001001000100000000 (
#185
0#
#186
1#
b000010010010 &
b01011100 '
b00001001001000000000 (
#187
0#
#188
1#
b000010010011 &
b01011101 '
b00001001001100000000 (
#189
0#
#190
1#
b000010010100 &
b01011110 '
b00001001010000000000 (
#191
0#
#192
1#
b000010010101 &
b01011111 '
b00001001010100000000 (
#193
0#
#194
1#
b000010010110 &
b01100000 '
b00001001011000000000 (
#195
0#
#196
1#
b000010010111 &
b01100001 '
b00001001011100000000 (
#197
0#
#198
1#
b000010011000 &
b01100010 '
b00001001100000000000 (
#199
0#
#200
1#
b000010011001 &
b01100011 '
b00001001100100000000 (
#201
0#
#202
1#
b000100000000 &
b01100100 '
b00010000000000000000 (
#203
0#
#204
1#
b000100000001 &
b01100101 '
b00010000000100000000 (
#205
0#
#206
1#
b000100000010 &
b01100110 '
b00010000001000000000 (
#207
0#
#208
1#
b000100000011 &
b01100111 '
b00010000001100000000 (
#209
0#
#210
1#
b000100000100 &
b01101000 '
b00010000010000000000 (
#211
0#
#212
1#
b000100000101 &
b01101001 '
b00010000010100000000 (
#213
0#
#214
1#
b000100000110 &
b01101010 '
b00010000011000000000 (
#215
0#
#216
1#
b000100000111 &
b01101011 '
b00010000011100000000 (
#217
0#
#218
1#
b000100001000 &
b01101100 '
b00010000100000000000 (
#219
0#
#220
1#
b000100001001 &
b01101101 '
b00010000100100000000 (
#221
0#
#222
1#
b000100010000 &
b01101110 '
b00010001000000000000 (
#223
0#
#224
1#
b000100010001 &
b01101111 '
b00010001000100000000 (
#225
0#
#226
1#
b000100010010 &
b01110000 '
b00010001001000000000 (
#227
0#
#228
1#
b000100010011 &
b01110001 '
b00010001001100000000 (
#229
0#
#230
1#
b000100010100 &
b01110010 '
b00010001010000000000 (
#231
0#
#232
1#
b000100010101 &
b01110011 '
b00010001010100000000 (
#233
0#
#234
1#
b000100010110 &
b01110100 '
b00010001011000000000 (
#235
0#
#236
1#
b000100010111 &
b01110101 '
b00010001011100000000 (
#237
0#
#238
1#
b000100011000 &
b01110110 '
b00010001100000000000 (
#239
0#
#240
1#
b000100011001 &
b01110111 '
b00010001100100000000 (
#241
0#
#242
1#
b000100100000 &
b01111000 '
b00010010000000000000 (
#243
0#
#244
1#
b000100100001 &
b01111001 '
b00010010000100000000 (
#245
0#
#246
1#
b000100100010 &
b01111010 '
b00010010001000000000 (
#247
0#
#248
1#
b000100100011 &
b01111011 '
b00010010001100000000 (
#249
0#
#250
1#
b000100100100 &
b01111100 '
b00010010010000000000 (
#251
0#
#252
1#
b000100100101 &
b01111101 '
b00010010010100000000 (
#253
0#
#254
1#
b000100100110 &
b01111110 '
b00010010011000000000 (
#255
0#
#256
1#
b000100100111 &
b01111111 '
b00010010011100000000 (
#257
0#
#258
1#
b000100101000 &
b10000000 '
b00010010100000000000 (
#259
0#
#260
1#
b000100101001 &
b10000001 '
b00010010100100000000 (
#261
0#
#262
1#
b000100110000 &
b10000010 '
b00010011000000000000 (
#263
0#
#264
1#
b000100110001 &
b10000011 '
b00010011000100000000 (
#265
0#
#266
1#
b000100110010 &
b10000100 '
b00010011001000000000 (
#267
0#
#268
1#
b000100110011 &
b10000101 '
b00010011001100000000 (
#269
0#
#270
1#
b000100110100 &
b10000110 '
b00010011010000000000 (
#271
0#
#272
1#
b000100110101 &
b10000111 '
b00010011010100000000 (
#273
0#
#274
1#
b000100110110 &
b10001000 '
b00010011011000000000 (
#275
0#
#276
1#
b000100110111 &
b10001001 '
b00010011011100000000 (
#277
0#
#278
1#
b000100111000 &
b10001010 '
b00010011100000000000 (
#279
0#
#280
1#
b000100111001 &
b10001011 '
b00010011100100000000 (
#281
0#
#282
1#
b000101000000 &
b10001100 '
b00010100000000000000 (
#283
0#
#284
1#
b000101000001 &
b10001101 '
b00010100000100000000 (
#285
0#
#286
1#
b000101000010 &
b10001110 '
b00010100001000000000 (
#287
0#
#288
1#
b000101000011 &
b10001111 '
b00010100001100000000 (
#289
0#
#290
1#
b000101000100 &
b10010000 '
b00010100010000000000 (
#291
0#
#292
1#
b000101000101 &
b10010001 '
b00010100010100000000 (
#293
0#
#294
1#
b000101000110 &
b10010010 '
b00010100011000000000 (
#295
0#
#296
1#
b000101000111 &
b10010011 '
b00010100011100000000 (
#297
0#
#298
1#
b000101001000 &
b10010100 '
b00010100100000000000 (
#299
0#
#300
1#
b000101001001 &
b10010101 '
b00010100100100000000 (
#301
0#
#302
1#
b000101010000 &
b10010110 '
b00010101000000000000 (
#303
0#
#304
1#
b000101010001 &
b10010111 '
b00010101000100000000 (
#305
0#
#306
1#
b000101010010 &
b10011000 '
b00010101001000000000 (
#307
0#
#308
1#
b000101010011 &
b10011001 '
b00010101001100000000 (
#309
0#
#310
1#
b000101010100 &
b10011010 '
b00010101010000000000 (
#311
0#
#312
1#
b000101010101 &
b10011011 '
b00010101010100000000 (
#313
0#
#314
1#
b000101010110 &
b10011100 '
b00010101011000000000 (
#315
0#
#316
1#
b000101010111 &
b10011101 '
b00010101011100000000 (
#317
0#
#318
1#
b000101011000 &
b10011110 '
b00010101100000000000 (
#319
0#
#320
1#
b000101011001 &
b10011111 '
b00010101100100000000 (
#321
0#
#322
1#
b000101100000 &
b10100000 '
b00010110000000000000 (
#323
0#
#324
1#
b000101100001 &
b10100001 '
b00010110000100000000 (
#325
0#
#326
1#
b000101100010 &
b10100010 '
b00010110001000000000 (
#327
0#
#328
1#
b000101100011 &
b10100011 '
b00010110001100000000 (
#329
0#
#330
1#
b000101100100 &
b10100100 '
b00010110010000000000 (
#331
0#
#332
1#
b000101100101 &
b10100101 '
b00010110010100000000 (
#333
0#
#334
1#
b000101100110 &
b10100110 '
b00010110011000000000 (
#335
0#
#336
1#
b000101100111 &
b10100111 '
b00010110011100000000 (
#337
0#
#338
1#
b000101101000 &
b10101000 '
b00010110100000000000 (
#339
0#
#340
1#
b000101101001 &
b10101001 '
b00010110100100000000 (
#341
0#
#342
1#
b000101110000 &
b10101010 '
b00010111000000000000 (
#343
0#
#344
1#
b000101110001 &
b10101011 '
b00010111000100000000 (
#345
0#
#346
1#
b000101110010 &
b10101100 '
b00010111001000000000 (
#347
0#
#348
1#
b000101110011 &
b10101101 '
b00010111001100000000 (
#349
0#
#350
1#
b000101110100 &
b10101110 '
b00010111010000000000 (
#351
0#
#352
1#
b000101110101 &
b10101111 '
b00010111010100000000 (
#353
0#
#354
1#
b000101110110 &
b10110000 '
b00010111011000000000 (
#355
0#
#356
1#
b000101110111 &
b10110001 '
b00010111011100000000 (
#357
0#
#358
1#
b000101111000 &
b10110010 '
b00010111100000000000 (
#359
0#
#360
1#
b000101111001 &
b10110011 '
b00010111100100000000 (
#361
0#
#362
1#
b000110000000 &
b10110100 '
b00011000000000000000 (
#363
0#
#364
1#
b000110000001 &
b10110101 '
b00011000000100000000 (
#365
0#
#366
1#
b000110000010 &
b10110110 '
b00011000001000000000 (
#367
0#
#368
1#
b000110000011 &
b10110111 '
b00011000001100000000 (
#369
0#
#370
1#
b000110000100 &
b10111000 '
b00011000010000000000 (
#371
0#
#372
1#
b000110000101 &
b10111001 '
b00011000010100000000 (
#373
0#
#374
1#
b000110000110 &
b10111010 '
b00011000011000000000 (
#375
0#
#376
1#
b000110000111 &
b10111011 '
b00011000011100000000 (
#377
0#
#378
1#
b000110001000 &
b10111100 '
b00011000100000000000 (
#379
0#
#380
1#
b000110001001 &
b10111101 '
b00011000100100000000 (
#381
0#
#382
1#
b000110010000 &
b10111110 '
b00011001000000000000 (
#383
0#
#384
1#
b000110010001 &
b10111111 '
b00011001000100000000 (
#385
0#
#386
1#
b000110010010 &
b11000000 '
b00011001001000000000 (
#387
0#
#388
1#
b000110010011 &
b11000001 '
b00011001001100000000 (
#389
0#
#390
1#
b000110010100 &
b11000010 '
b00011001010000000000 (
#391
0#
#392
1#
b000110010101 &
b11000011 '
b00011001010100000000 (
#393
0#
#394
1#
b000110010110 &
b11000100 '
b00011001011000000000 (
#395
0#
#396
1#
b000110010111 &
b11000101 '
b00011001011100000000 (
#397
0#
#398
1#
b000110011000 &
b11000110 '
b00011001100000000000 (
#399
0#
#400
1#
b000110011001 &
b11000111 '
b00011001100100000000 (
#401
0#
#402
1#
b001000000000 &
b11001000 '
b00100000000000000000 (
#403
0#
#404
1#
b001000000001 &
b11001001 '
b00100000000100000000 (
#405
0#
#406
1#
b001000000010 &
b11001010 '
b00100000001000000000 (
#407
0#
#408
1#
b001000000011 &
b11001011 '
b00100000001100000000 (
#409
0#
#410
1#
b001000000100 &
b11001100 '
b00100000010000000000 (
#411
0#
#412
1#
b001000000101 &
b11001101 '
b00100000010100000000 (
#413
0#
#414
1#
b001000000110 &
b11001110 '
b00100000011000000000 (
#415
0#
#416
1#
b001000000111 &
b11001111 '
b00100000011100000000 (
#417
0#
#418
1#
b001000001000 &
b11010000 '
b00100000100000000000 (
#419
0#
#420
1#
b001000001001 &
b11010001 '
b00100000100100000000 (
#421
0#
#422
1#
b001000010000 &
b11010010 '
b00100001000000000000 (
#423
0#
#424
1#
b001000010001 &
b11010011 '
b00100001000100000000 (
#425
0#
#426
1#
b001000010010 &
b11010100 '
b00100001001000000000 (
#427
0#
#428
1#
b001000010011 &
b11010101 '
b00100001001100000000 (
#429
0#
#430
1#
b001000010100 &
b11010110 '
b00100001010000000000 (
#431
0#
#432
1#
b001000010101 &
b11010111 '
b00100001010100000000 (
#433
0#
#434
1#
b001000010110 &
b11011000 '
b00100001011000000000 (
#435
0#
#436
1#
b001000010111 &
b11011001 '
b00100001011100000000 (
#437
0#
#438
1#
b001000011000 &
b11011010 '
b00100001100000000000 (
#439
0#
#440
1#
b001000011001 &
b11011011 '
b00100001100100000000 (
#441
0#
#442
1#
b001000100000 &
b11011100 '
b00100010000000000000 (
#443
0#
#444
1#
b001000100001 &
b11011101 '
b00100010000100000000 (
#445
0#
#446
1#
b001000100010 &
b11011110 '
b00100010001000000000 (
#447
0#
#448
1#
b001000100011 &
b11011111 '
b00100010001100000000 (
#449
0#
#450
1#
b001000100100 &
b11100000 '
b00100010010000000000 (
#451
0#
#452
1#
b001000100101 &
b11100001 '
b00100010010100000000 (
#453
0#
#454
1#
b001000100110 &
b11100010 '
b00100010011000000000 (
#455
0#
#456
1#
b001000100111 &
b11100011 '
b00100010011100000000 (
#457
0#
#458
1#
b001000101000 &
b11100100 '
b00100010100000000000 (
#459
0#
#460
1#
b001000101001 &
b11100101 '
b00100010100100000000 (
#461
0#
#462
1#
b001000110000 &
b11100110 '
b00100011000000000000 (
#463
0#
#464
1#
b001000110001 &
b11100111 '
b00100011000100000000 (
#465
0#
#466
1#
b001000110010 &
b11101000 '
b00100011001000000000 (
#467
0#
#468
1#
b001000110011 &
b11101001 '
b00100011001100000000 (
#469
0#
#470
1#
b001000110100 &
b11101010 '
b00100011010000000000 (
#471
0#
#472
1#
b001000110101 &
b11101011 '
b00100011010100000000 (
#473
0#
#474
1#
b001000110110 &
b11101100 '
b00100011011000000000 (
#475
0#
#476
1#
b001000110111 &
b11101101 '
b00100011011100000000 (
#477
0#
#478
1#
b001000111000 &
b11101110 '
b00100011100000000000 (
#479
0#
#480
1#
b001000111001 &
b11101111 '
b00100011100100000000 (
#481
0#
#482
1#
b001001000000 &
b11110000 '
b00100100000000000000 (
#483
0#
#484
1#
b001001000001 &
b11110001 '
b00100100000100000000 (
#485
0#
#486
1#
b001001000010 &
b11110010 '
b00100100001000000000 (
#487
0#
#488
1#
b001001000011 &
b11110011 '
b00100100001100000000 (
#489
0#
#490
1#
b001001000100 &
b11110100 '
b00100100010000000000 (
#491
0#
#492
1#
b001001000101 &
b11110101 '
b00100100010100000000 (
#493
0#
#494
1#
b001001000110 &
b11110110 '
b00100100011000000000 (
#495
0#
#496
1#
b001001000111 &
b11110111 '
b00100100011100000000 (
#497
0#
#498
1#
b001001001000 &
b11111000 '
b00100100100000000000 (
#499
0#
#500
1#
b001001001001 &
b11111001 '
b00100100100100000000 (
#501
0#
#502
1#
b001001010000 &
b11111010 '
b00100101000000000000 (
#503
0#
#504
1#
b001001010001 &
b11111011 '
b00100101000100000000 (
#505
0#
#506
1#
b001001010010 &
b11111100 '
b00100101001000000000 (
#507
0#
#508
1#
b001001010011 &
b11111101 '
b00100101001100000000 (
#509
0#
#510
1#
b001001010100 &
b11111110 '
b00100101010000000000 (
