task1/counter.sv
module counter #(parameter WIDTH = 8)
(input logic clk, // Clock
 input logic rst, // Reset
 input logic en, // Counter enable
 output logic[WIDTH-1:0] count); // Counter output
    
    always_ff @(posedge clk, posedge rst)
        if (rst)
            count <= {WIDTH{1'b0}};
        else
            count <= count + {{WIDTH-1{1'b0}}, en};

endmodule

task1/counter.vcd
$version Generated by VerilatedVcd $end
$date Sat Oct 22 15:28:21 2022 $end
$timescale 1ps $end

 $scope module TOP $end
  $var wire  1 # clk $end
  $var wire  8 & count [7:0] $end
  $var wire  1 % en $end
  $var wire  1 $ rst $end
  $scope module counter $end
   $var wire 32 ' WIDTH [31:0] $end
   $var wire  1 # clk $end
   $var wire  8 & count [7:0] $end
   $var wire  1 % en $end
   $var wire  1 $ rst $end
  $upscope $end
 $upscope $end
$enddefinitions $end


#0
1#
1$
0%
b00000000 &
b00000000000000000000000000001000 '
#1
0#
#2
1#
0$
1%
#3
0#
#4
1#
b00000001 &
#5
0#
#6
1#
b00000010 &
#7
0#
#8
1#
b00000011 &
#9
0#
#10
1#
b00000100 &
#11
0#
#12
1#
b00000101 &
#13
0#
#14
1#
b00000110 &
#15
0#
#16
1#
b00000111 &
#17
0#
#18
1#
b00001000 &
#19
0#
#20
1#
0%
b00001001 &
#21
0#
#22
1#
#23
0#
#24
1#
#25
0#
#26
1#
1%
#27
0#
#28
1#
b00001010 &
#29
0#
#30
1#
b00001011 &
#31
0#
#32
1#
1$
b00001100 &
#33
0#
b00000000 &
#34
1#
0$
#35
0#
#36
1#
b00000001 &
#37
0#
#38
1#
b00000010 &
#39
0#
#40
1#
b00000011 &
#41
0#
#42
1#
b00000100 &
#43
0#
#44
1#
b00000101 &
#45
0#
#46
1#
b00000110 &
#47
0#
#48
1#
b00000111 &
#49
0#
#50
1#
b00001000 &
#51
0#
#52
1#
0%
b00001001 &
#53
0#
#54
1#
#55
0#
#56
1#
#57
0#
#58
1#
1%
#59
0#
#60
1#
b00001010 &
#61
0#
#62
1#
b00001011 &
#63
0#
#64
1#
b00001100 &
#65
0#
#66
1#
b00001101 &
#67
0#
#68
1#
b00001110 &
#69
0#
#70
1#
b00001111 &
#71
0#
#72
1#
b00010000 &
#73
0#
#74
1#
b00010001 &
#75
0#
#76
1#
b00010010 &
#77
0#
#78
1#
b00010011 &
#79
0#
#80
1#
b00010100 &
#81
0#
#82
1#
b00010101 &
#83
0#
#84
1#
b00010110 &
#85
0#
#86
1#
b00010111 &
#87
0#
#88
1#
b00011000 &
#89
0#
#90
1#
b00011001 &
#91
0#
#92
1#
b00011010 &
#93
0#
#94
1#
b00011011 &
#95
0#
#96
1#
b00011100 &
#97
0#
#98
1#
b00011101 &
#99
0#
#100
1#
b00011110 &
#101
0#
#102
1#
b00011111 &
#103
0#
#104
1#
b00100000 &
#105
0#
#106
1#
b00100001 &
#107
0#
#108
1#
b00100010 &
#109
0#
#110
1#
b00100011 &
#111
0#
#112
1#
b00100100 &
#113
0#
#114
1#
b00100101 &
#115
0#
#116
1#
b00100110 &
#117
0#
#118
1#
b00100111 &
#119
0#
#120
1#
b00101000 &
#121
0#
#122
1#
b00101001 &
#123
0#
#124
1#
b00101010 &
#125
0#
#126
1#
b00101011 &
#127
0#
#128
1#
b00101100 &
#129
0#
#130
1#
b00101101 &
#131
0#
#132
1#
b00101110 &
#133
0#
#134
1#
b00101111 &
#135
0#
#136
1#
b00110000 &
#137
0#
#138
1#
b00110001 &
#139
0#
#140
1#
b00110010 &
#141
0#
#142
1#
b00110011 &
#143
0#
#144
1#
b00110100 &
#145
0#
#146
1#
b00110101 &
#147
0#
#148
1#
b00110110 &
#149
0#
#150
1#
b00110111 &
#151
0#
#152
1#
b00111000 &
#153
0#
#154
1#
b00111001 &
#155
0#
#156
1#
b00111010 &
#157
0#
#158
1#
b00111011 &
#159
0#
#160
1#
b00111100 &
#161
0#
#162
1#
b00111101 &
#163
0#
#164
1#
b00111110 &
#165
0#
#166
1#
b00111111 &
#167
0#
#168
1#
b01000000 &
#169
0#
#170
1#
b01000001 &
#171
0#
#172
1#
b01000010 &
#173
0#
#174
1#
b01000011 &
#175
0#
#176
1#
b01000100 &
#177
0#
#178
1#
b01000101 &
#179
0#
#180
1#
b01000110 &
#181
0#
#182
1#
b01000111 &
#183
0#
#184
1#
b01001000 &
#185
0#
#186
1#
b01001001 &
#187
0#
#188
1#
b01001010 &
#189
0#
#190
1#
b01001011 &
#191
0#
#192
1#
b01001100 &
#193
0#
#194
1#
b01001101 &
#195
0#
#196
1#
b01001110 &
#197
0#
#198
1#
b01001111 &
