task2/counter.sv
module counter #(parameter WIDTH = 8)
(input logic clk, // Clock
 input logic rst, // Reset
 input logic en, // Counter enable
 output logic[WIDTH-1:0] count); // Counter output
    
    always_ff @(posedge clk)
        if (rst)
            count <= {WIDTH{1'b0}};
        else if (en)
            count <= count + {{WIDTH-1{1'b0}}, 1'b1};
        else
            count <= count - {{WIDTH-1{1'b0}}, 1'b1};

endmodule

task2/counter.vcd
$version Generated by VerilatedVcd $end
$date Tue Oct 25 14:11:15 2022 $end
$timescale 1ps $end

 $scope module TOP $end
  $var wire  1 # clk $end
  $var wire  8 & count [7:0] $end
  $var wire  1 % en $end
  $var wire  1 $ rst $end
  $scope module counter $end
   $var wire 32 ' WIDTH [31:0] $end
   $var wire  1 # clk $end
   $var wire  8 & count [7:0] $end
   $var wire  1 % en $end
   $var wire  1 $ rst $end
  $upscope $end
 $upscope $end
$enddefinitions $end


#0
1#
1$
0%
b00000000 &
b00000000000000000000000000001000 '
#1
0#
#2
1#
#3
0#
#4
1#
#5
0#
#6
1#
0$
#7
0#
#8
1#
b11111111 &
#9
0#
#10
1#
b11111110 &
#11
0#
#12
1#
b11111101 &
#13
0#
#14
1#
b11111100 &
#15
0#
#16
1#
b11111011 &
#17
0#
#18
1#
b11111010 &
#19
0#
#20
1#
b11111001 &
#21
0#
#22
1#
b11111000 &
#23
0#
#24
1#
b11110111 &
#25
0#
#26
1#
b11110110 &
#27
0#
#28
1#
b11110101 &
#29
0#
#30
1#
b11110100 &
#31
0#
#32
1#
b11110011 &
#33
0#
#34
1#
b11110010 &
#35
0#
#36
1#
b11110001 &
#37
0#
#38
1#
b11110000 &
#39
0#
#40
1#
b11101111 &
#41
0#
#42
1#
b11101110 &
#43
0#
#44
1#
b11101101 &
#45
0#
#46
1#
b11101100 &
#47
0#
#48
1#
b11101011 &
#49
0#
#50
1#
b11101010 &
#51
0#
#52
1#
b11101001 &
#53
0#
#54
1#
b11101000 &
#55
0#
#56
1#
b11100111 &
#57
0#
#58
1#
b11100110 &
#59
0#
#60
1#
b11100101 &
#61
0#
#62
1#
b11100100 &
#63
0#
#64
1#
b11100011 &
#65
0#
#66
1#
b11100010 &
#67
0#
#68
1#
b11100001 &
#69
0#
#70
1#
b11100000 &
#71
0#
#72
1#
b11011111 &
#73
0#
#74
1#
b11011110 &
#75
0#
#76
1#
b11011101 &
#77
0#
#78
1#
b11011100 &
#79
0#
#80
1#
b11011011 &
#81
0#
#82
1#
b11011010 &
#83
0#
#84
1#
b11011001 &
#85
0#
#86
1#
b11011000 &
#87
0#
#88
1#
b11010111 &
#89
0#
#90
1#
b11010110 &
#91
0#
#92
1#
b11010101 &
#93
0#
#94
1#
b11010100 &
#95
0#
#96
1#
b11010011 &
#97
0#
#98
1#
b11010010 &
#99
0#
#100
1#
b11010001 &
#101
0#
#102
1#
b11010000 &
#103
0#
#104
1#
b11001111 &
#105
0#
#106
1#
b11001110 &
#107
0#
#108
1#
b11001101 &
#109
0#
#110
1#
b11001100 &
#111
0#
#112
1#
1%
b11001011 &
#113
0#
#114
1#
b11001100 &
#115
0#
#116
1#
b11001101 &
#117
0#
#118
1#
b11001110 &
#119
0#
#120
1#
b11001111 &
#121
0#
#122
1#
b11010000 &
#123
0#
#124
1#
b11010001 &
#125
0#
#126
1#
b11010010 &
#127
0#
#128
1#
b11010011 &
#129
0#
#130
1#
b11010100 &
#131
0#
#132
1#
b11010101 &
#133
0#
#134
1#
0%
b11010110 &
#135
0#
#136
1#
b11010101 &
#137
0#
#138
1#
b11010100 &
#139
0#
#140
1#
b11010011 &
#141
0#
#142
1#
b11010010 &
#143
0#
#144
1#
b11010001 &
#145
0#
#146
1#
b11010000 &
#147
0#
#148
1#
b11001111 &
#149
0#
#150
1#
b11001110 &
#151
0#
#152
1#
b11001101 &
#153
0#
#154
1#
b11001100 &
#155
0#
#156
1#
b11001011 &
#157
0#
#158
1#
b11001010 &
#159
0#
#160
1#
b11001001 &
#161
0#
#162
1#
b11001000 &
#163
0#
#164
1#
b11000111 &
#165
0#
#166
1#
b11000110 &
#167
0#
#168
1#
b11000101 &
#169
0#
#170
1#
1%
b11000100 &
#171
0#
#172
1#
b11000101 &
#173
0#
#174
1#
b11000110 &
#175
0#
#176
1#
b11000111 &
#177
0#
#178
1#
b11001000 &
#179
0#
#180
1#
b11001001 &
#181
0#
#182
1#
b11001010 &
#183
0#
#184
1#
b11001011 &
#185
0#
#186
1#
b11001100 &
#187
0#
#188
1#
b11001101 &
#189
0#
#190
1#
b11001110 &
#191
0#
#192
1#
b11001111 &
#193
0#
#194
1#
b11010000 &
#195
0#
#196
1#
b11010001 &
#197
0#
#198
1#
b11010010 &
